pravah_protocols/AirQuality_pb2.py
pravah_protocols/Covid19District_pb2.py
pravah_protocols/FeedHeaderStatic_pb2.py
pravah_protocols/FeedHeader_pb2.py
pravah_protocols/FlightData_pb2.py
pravah_protocols/FlightLog_pb2.py
pravah_protocols/HospitalCapacity_pb2.py
pravah_protocols/PermissionArtefact_pb2.py
pravah_protocols/PublicBus_pb2.py
pravah_protocols/SolarPowerProductionStatic_pb2.py
pravah_protocols/SolarPowerProduction_pb2.py
pravah_protocols/__init__.py
pravah_protocols-0.0.7.dist-info/METADATA
pravah_protocols-0.0.7.dist-info/WHEEL
pravah_protocols-0.0.7.dist-info/top_level.txt
pravah_protocols-0.0.7.dist-info/RECORD
